[
    {
        "nombre": "Jhojan Espinosa",
        "email": "jhojan@example.com",
        "password_hash": "$2b$12$ZkoSLgUxCXuOIU3HtnZgIODvHc9QCDe0XB18RzKmNmSSYhWOolvVK",
        "ingreso_mensual": 1620000.0,
        "saldoRestante": 1020000.0,
        "gastosMensuales": 150000.0,
        "categorias": {
            "alimentacion": {
                "presupuestoInicial": 400000.0,
                "saldoRestante": 250000.0,
                "gastos": 150000.0,
                "movimientos": [
                    {
                        "id": "37409dde-0524-41a1-8611-6043a0ef7883",
                        "categoria": "Alimentacion",
                        "monto": 150000.0,
                        "descripcion": "Carne",
                        "fecha": "2025-11-22 14:32:29"
                    }
                ],
                "nombre": "Alimentacion"
            },
            "transporte": {
                "presupuestoInicial": 200000.0,
                "saldoRestante": 200000.0,
                "gastos": 0.0,
                "movimientos": [],
                "nombre": "Transporte"
            },
            "hogar": {
                "presupuestoInicial": 0,
                "saldoRestante": 0,
                "gastos": 0,
                "movimientos": [],
                "nombre": "Hogar"
            },
            "otros": {
                "presupuestoInicial": 0,
                "saldoRestante": 0,
                "gastos": 0,
                "movimientos": [],
                "nombre": "Otros"
            }
        },
        "historial": [
            {
                "id": "37409dde-0524-41a1-8611-6043a0ef7883",
                "categoria": "Alimentacion",
                "monto": 150000.0,
                "descripcion": "Carne",
                "fecha": "2025-11-22 14:32:29"
            }
        ],
        "categorias_arbol": {
            "name": "Categorias",
            "presupuesto": 0.0,
            "gastos": 0.0,
            "saldoRestante": 0.0,
            "movimientos": [],
            "children": [
                {
                    "name": "Alimentacion",
                    "presupuesto": 400000.0,
                    "gastos": 150000.0,
                    "saldoRestante": 250000.0,
                    "movimientos": [
                        {
                            "id": "37409dde-0524-41a1-8611-6043a0ef7883",
                            "categoria": "Alimentacion",
                            "monto": 150000.0,
                            "descripcion": "Carne",
                            "fecha": "2025-11-22 14:32:29"
                        }
                    ],
                    "children": [],
                    "total_gastos_recursive": 150000.0,
                    "total_presupuesto_recursive": 400000.0
                },
                {
                    "name": "Transporte",
                    "presupuesto": 200000.0,
                    "gastos": 0.0,
                    "saldoRestante": 200000.0,
                    "movimientos": [],
                    "children": [],
                    "total_gastos_recursive": 0.0,
                    "total_presupuesto_recursive": 200000.0
                },
                {
                    "name": "Hogar",
                    "presupuesto": 0.0,
                    "gastos": 0.0,
                    "saldoRestante": 0.0,
                    "movimientos": [],
                    "children": [],
                    "total_gastos_recursive": 0.0,
                    "total_presupuesto_recursive": 0.0
                },
                {
                    "name": "Otros",
                    "presupuesto": 0.0,
                    "gastos": 0.0,
                    "saldoRestante": 0.0,
                    "movimientos": [],
                    "children": [],
                    "total_gastos_recursive": 0.0,
                    "total_presupuesto_recursive": 0.0
                }
            ],
            "total_gastos_recursive": 150000.0,
            "total_presupuesto_recursive": 600000.0
        },
        "ArbolGeneral": {
            "name": "Categorias",
            "presupuesto": 0.0,
            "gastos": 0.0,
            "saldoRestante": 0.0,
            "movimientos": [],
            "children": [
                {
                    "name": "Alimentacion",
                    "presupuesto": 400000.0,
                    "gastos": 150000.0,
                    "saldoRestante": 250000.0,
                    "movimientos": [
                        {
                            "id": "37409dde-0524-41a1-8611-6043a0ef7883",
                            "categoria": "Alimentacion",
                            "monto": 150000.0,
                            "descripcion": "Carne",
                            "fecha": "2025-11-22 14:32:29"
                        }
                    ],
                    "children": [],
                    "total_gastos_recursive": 150000.0,
                    "total_presupuesto_recursive": 400000.0
                },
                {
                    "name": "Transporte",
                    "presupuesto": 200000.0,
                    "gastos": 0.0,
                    "saldoRestante": 200000.0,
                    "movimientos": [],
                    "children": [],
                    "total_gastos_recursive": 0.0,
                    "total_presupuesto_recursive": 200000.0
                },
                {
                    "name": "Hogar",
                    "presupuesto": 0.0,
                    "gastos": 0.0,
                    "saldoRestante": 0.0,
                    "movimientos": [],
                    "children": [],
                    "total_gastos_recursive": 0.0,
                    "total_presupuesto_recursive": 0.0
                },
                {
                    "name": "Otros",
                    "presupuesto": 0.0,
                    "gastos": 0.0,
                    "saldoRestante": 0.0,
                    "movimientos": [],
                    "children": [],
                    "total_gastos_recursive": 0.0,
                    "total_presupuesto_recursive": 0.0
                }
            ],
            "total_gastos_recursive": 150000.0,
            "total_presupuesto_recursive": 600000.0
        },
        "alertas": []
    }
]